{
  "pools": [
    {
      "rolls": 1,
      "entries": [
        {
          "type": "minecraft:item",
          "name": "minecraft:cooked_beef",
          "functions": [
            {
              "function": "minecraft:set_components",
              "components": {
                "minecraft:item_name": "\"Golden Steak\"",
                "minecraft:food": {
                  "nutrition": 10,
                  "saturation": 14.8,
                  "can_always_eat": false
                },
                "minecraft:item_model": "gilded:golden_cooked_beef"
              }
            }
          ]
        }
      ]
    }
  ]
}